README.txt
setup.cfg
setup.py
docs/HISTORY.txt
docs/INSTALL.txt
docs/LICENSE.GPL
docs/LICENSE.txt
ngi/__init__.py
ngi.theme.simple.egg-info/PKG-INFO
ngi.theme.simple.egg-info/SOURCES.txt
ngi.theme.simple.egg-info/dependency_links.txt
ngi.theme.simple.egg-info/entry_points.txt
ngi.theme.simple.egg-info/namespace_packages.txt
ngi.theme.simple.egg-info/not-zip-safe
ngi.theme.simple.egg-info/requires.txt
ngi.theme.simple.egg-info/top_level.txt
ngi/theme/__init__.py
ngi/theme/simple/__init__.py
ngi/theme/simple/config.py
ngi/theme/simple/configure.zcml
ngi/theme/simple/interfaces.py
ngi/theme/simple/overrides.zcml
ngi/theme/simple/tests.py
ngi/theme/simple/version.txt
ngi/theme/simple/browser/__init__.py
ngi/theme/simple/browser/configure.zcml
ngi/theme/simple/browser/footer.pt
ngi/theme/simple/browser/footer.py
ngi/theme/simple/browser/logo.pt
ngi/theme/simple/browser/logo.py
ngi/theme/simple/browser/pref_form.py
ngi/theme/simple/locales/ngi.theme.simple.pot
ngi/theme/simple/locales/ja/LC_MESSAGES/ngi.theme.simple.mo
ngi/theme/simple/locales/ja/LC_MESSAGES/ngi.theme.simple.po
ngi/theme/simple/profiles/default/controlpanel.xml
ngi/theme/simple/profiles/default/metadata.xml
ngi/theme/simple/profiles/default/registry.xml
ngi/theme/simple/static/simple_theme_icon.png