Metadata-Version: 1.0
Name: ngi.theme.simple
Version: 1.0b7
Summary: It is easy to setup the logo and footer using the control panel.
Home-page: http://code.google.com/p/plone4-simpletheme/
Author: Takashi NAGAI
Author-email: nagai@ngi644.net
License: GPL
Keywords: Plone Theme
Platform: UNKNOWN
Classifier: Framework :: Plone
Classifier: Programming Language :: Python
